stata_mcp/__init__.py
stata_mcp/mcp_servers.py
stata_mcp/agent_as_tool/__init__.py
stata_mcp/agent_as_tool/set_model.py
stata_mcp/agent_as_tool/stata_agent.py
stata_mcp/cli/__init__.py
stata_mcp/cli/_cli.py
stata_mcp/core/__init__.py
stata_mcp/core/data_info/__init__.py
stata_mcp/core/data_info/_base.py
stata_mcp/core/data_info/csv.py
stata_mcp/core/data_info/dta.py
stata_mcp/core/stata/__init__.py
stata_mcp/core/stata/stata_controller/__init__.py
stata_mcp/core/stata/stata_controller/controller.py
stata_mcp/core/stata/stata_do/__init__.py
stata_mcp/core/stata/stata_do/do.py
stata_mcp/core/stata/stata_finder/__init__.py
stata_mcp/core/stata/stata_finder/base.py
stata_mcp/core/stata/stata_finder/finder.py
stata_mcp/core/stata/stata_finder/linux.py
stata_mcp/core/stata/stata_finder/macos.py
stata_mcp/core/stata/stata_finder/windows.py
stata_mcp/evaluate/__init__.py
stata_mcp/evaluate/_model.py
stata_mcp/evaluate/advice.py
stata_mcp/evaluate/agent_runner.py
stata_mcp/evaluate/score_it.py
stata_mcp/mode/__init__.py
stata_mcp/mode/langchain_agent.py
stata_mcp/mode/pmp/__init__.py
stata_mcp/mode/pmp/prompt_generator.py
stata_mcp/sandbox/README.md
stata_mcp/sandbox/__init__.py
stata_mcp/sandbox/core/__init__.py
stata_mcp/sandbox/core/execute.py
stata_mcp/sandbox/core/result_processor.py
stata_mcp/sandbox/core/sandbox_manager.py
stata_mcp/sandbox/jupyter_manager/__init__.py
stata_mcp/sandbox/jupyter_manager/kernel_manager.py
stata_mcp/sandbox/jupyter_manager/kernel_pool.py
stata_mcp/utils/__init__.py
stata_mcp/utils/usable.py
stata_mcp/utils/Installer/__init__.py
stata_mcp/utils/Installer/installer.py
stata_mcp/utils/Prompt/__init__.py
stata_mcp/utils/Prompt/string.py
iflow_mcp_stata_mcp-1.11.2.dist-info/METADATA
iflow_mcp_stata_mcp-1.11.2.dist-info/WHEEL
iflow_mcp_stata_mcp-1.11.2.dist-info/entry_points.txt
iflow_mcp_stata_mcp-1.11.2.dist-info/licenses/LICENSE
iflow_mcp_stata_mcp-1.11.2.dist-info/RECORD
