Metadata-Version: 2.4
Name: iflow-mcp_stata-mcp
Version: 1.11.2
Summary: Let LLM help you achieve your regression analysis with Stata
Project-URL: Homepage, https://www.statamcp.com
Project-URL: Source, https://github.com/sepinetam/stata-mcp
Author-email: Song Tan <sepine@statamcp.com>
License: Apache-2.0
License-File: LICENSE
Requires-Python: >=3.11
Requires-Dist: langchain-mcp-adapters>=0.1.10
Requires-Dist: langchain-openai>=0.3.33
Requires-Dist: langchain>=0.3.27
Requires-Dist: langgraph>=0.6.7
Requires-Dist: mcp[cli]>=1.16.0
Requires-Dist: openai-agents>=0.3.2
Requires-Dist: openai>=1.109.1
Requires-Dist: openpyxl>=3.1.5
Requires-Dist: pandas>=2.3.0
Requires-Dist: pathvalidate>=3.3.1
Requires-Dist: pexpect>=4.9.0
Requires-Dist: python-dotenv>=1.1.1
